{
    "cn": "Tree",
    "ct": 1,
    "frag": {
        "dt": "AntDesign.Tree\u00601[System.String], AntDesign",
        "valt": "System.String",
        "params": []
    },
    "pgroups": [],
    "childs": [],
    "sptds": false,
    "order": 31,
    "pub": 1,
    "mt": "2025-01-02T14:51:13.4270145Z",
    "id": "hepj4qcm",
    "libid": "antdesign",
    "compid": "sonvddk21",
    "lb": "树",
    "container": false,
    "stl": {
        "itemh": 85,
        "labelw": 180,
        "display": "inline",
        "pos": "static"
    },
    "ev": {},
    "ds": {
        "dst": 0
    }
}